arcGisFeatureCash/__init__.py
arcGisFeatureCash/arcGisScraper.py
arcGisFeatureCash/featureLayer.py
arcGisFeatureCash/featureService.py
arcGisFeatureCash/models/__init__.py
arcGisFeatureCash/models/attributes.py
arcGisFeatureCash/models/feature.py
arcGisFeatureCash/models/geometry.py
arcGisFeatureCash/utils/__init__.py
arcGisFeatureCash/utils/helpers.py
arcGisFeatureCash/utils/immutableList.py
arcGisFeatureCash/utils/log.py
arcgisfeaturecash-0.1.0.dist-info/LICENSE.md
arcgisfeaturecash-0.1.0.dist-info/WHEEL
arcgisfeaturecash-0.1.0.dist-info/METADATA
arcgisfeaturecash-0.1.0.dist-info/RECORD
