Metadata-Version: 2.1
Name: arcGisFeatureCash
Version: 0.1.0
Summary: Package to cash a arcgis feature service
Author-email: Hzd <Hazedd@users.noreply.github.com>
Requires-Python: >3.10
Classifier: Development Status :: 1 - Planning
Classifier: Intended Audience :: End Users/Desktop
Classifier: Programming Language :: Python :: 3.10
Classifier: Programming Language :: Python :: 3.11
Classifier: Programming Language :: Python :: 3.12
Classifier: License :: OSI Approved :: MIT License
Requires-Dist: httpx
Requires-Dist: loguru
Requires-Dist: shapely
Requires-Dist: bumpversion ; extra == "dev"
Requires-Dist: mypy ; extra == "dev"
Requires-Dist: pytest ; extra == "dev"
Requires-Dist: pytest-asyncio ; extra == "dev"
Requires-Dist: pytest-cov ; extra == "dev"
Requires-Dist: pytest-mock ; extra == "dev"
Requires-Dist: pre-commit ; extra == "dev"
Requires-Dist: ruff ; extra == "dev"
Provides-Extra: dev
